apywire/__init__.py
apywire/__main__.py
apywire/compiler.py
apywire/constants.py
apywire/exceptions.py
apywire/formats.py
apywire/generator.py
apywire/py.typed
apywire/runtime.py
apywire/threads.py
apywire/wiring.c
apywire/wiring.cpython-313-x86_64-linux-gnu.so
apywire/wiring.py
examples/basic_app/app.py
examples/kv_store/main.py
tests/__init__.py
tests/test_cli.py
tests/test_compile_aio.py
tests/test_constant_placeholders.py
tests/test_edge_cases.py
tests/test_factory_methods.py
tests/test_formats.py
tests/test_generator.py
tests/test_internals.py
tests/test_single.py
tests/test_stdlib_compat.py
tests/test_threading.py
apywire-0.2.0.dist-info/METADATA
apywire-0.2.0.dist-info/WHEEL
apywire-0.2.0.dist-info/top_level.txt
apywire-0.2.0.dist-info/RECORD
apywire-0.2.0.dist-info/licenses/LICENSE
