Metadata-Version: 2.4
Name: apywire
Version: 0.2.0
Summary: A package to wire up objects
Author-email: Alexandre Gomes Gaigalas <alganet@gmail.com>
Maintainer-email: Alexandre Gomes Gaigalas <alganet@gmail.com>
License-Expression: ISC
Project-URL: Homepage, https://github.com/alganet/apywire
Project-URL: Repository, https://github.com/alganet/apywire
Project-URL: Issues, https://github.com/alganet/apywire/issues
Keywords: object,wiring,dependency,injection
Classifier: Development Status :: 3 - Alpha
Classifier: Intended Audience :: Developers
Classifier: Programming Language :: Python :: 3
Classifier: Programming Language :: Python :: 3.12
Classifier: Programming Language :: Python :: 3.13
Classifier: Programming Language :: Python :: 3.14
Classifier: Topic :: Software Development :: Libraries :: Python Modules
Requires-Python: >=3.12
License-File: LICENSE
Provides-Extra: dev
Requires-Dist: auditwheel; extra == "dev"
Requires-Dist: black; extra == "dev"
Requires-Dist: build; extra == "dev"
Requires-Dist: coverage; extra == "dev"
Requires-Dist: Cython; extra == "dev"
Requires-Dist: flake8-pyproject; extra == "dev"
Requires-Dist: flake8; extra == "dev"
Requires-Dist: isort; extra == "dev"
Requires-Dist: mike; extra == "dev"
Requires-Dist: mkdocs-autorefs; extra == "dev"
Requires-Dist: mkdocs-material; extra == "dev"
Requires-Dist: mkdocs; extra == "dev"
Requires-Dist: mkdocstrings[python]; extra == "dev"
Requires-Dist: mypy; extra == "dev"
Requires-Dist: pytest-cov; extra == "dev"
Requires-Dist: pytest; extra == "dev"
Requires-Dist: reuse; extra == "dev"
Requires-Dist: twine; extra == "dev"
Requires-Dist: tomli_w; extra == "dev"
Requires-Dist: types-setuptools; extra == "dev"
Dynamic: license-file
Dynamic: requires-python
